ReversingLabs/__init__.py
ReversingLabs/SDK/__init__.py
ReversingLabs/SDK/a1000.py
ReversingLabs/SDK/advanced.py
ReversingLabs/SDK/fie.py
ReversingLabs/SDK/helper.py
ReversingLabs/SDK/ticloud.py
ReversingLabs/SDK/tiscale.py
reversinglabs_sdk_py3-2.11.4.dist-info/licenses/LICENSE
reversinglabs_sdk_py3-2.11.4.dist-info/METADATA
reversinglabs_sdk_py3-2.11.4.dist-info/WHEEL
reversinglabs_sdk_py3-2.11.4.dist-info/top_level.txt
reversinglabs_sdk_py3-2.11.4.dist-info/RECORD
