Metadata-Version: 2.4
Name: reversinglabs-sdk-py3
Version: 2.11.4
Summary: Python SDK for using ReversingLabs services.
Home-page: https://github.com/reversinglabs/reversinglabs-sdk-py3
Author: ReversingLabs
Author-email: support@reversinglabs.com
License: MIT
Project-URL: Documentation, https://github.com/reversinglabs/reversinglabs-sdk-py3/blob/main/README.md
Project-URL: Source, https://github.com/reversinglabs/reversinglabs-sdk-py3
Project-URL: Changes, https://github.com/reversinglabs/reversinglabs-sdk-py3/blob/main/CHANGELOG.md
Classifier: Development Status :: 5 - Production/Stable
Classifier: Intended Audience :: Developers
Classifier: Natural Language :: English
Classifier: Programming Language :: Python
Classifier: Programming Language :: Python :: 3
Classifier: Programming Language :: Python :: 3.9
Classifier: Programming Language :: Python :: 3.10
Classifier: Programming Language :: Python :: 3.11
Classifier: Programming Language :: Python :: 3.12
Classifier: Programming Language :: Python :: 3.13
Classifier: Programming Language :: Python :: Implementation :: CPython
Classifier: Topic :: Security
Classifier: Topic :: Software Development :: Libraries :: Python Modules
Requires-Python: >=3.9
License-File: LICENSE
Requires-Dist: requests>=2.32.4
Provides-Extra: test
Requires-Dist: pytest; extra == "test"
Provides-Extra: largefiles
Requires-Dist: requests-toolbelt; extra == "largefiles"
Dynamic: author
Dynamic: author-email
Dynamic: classifier
Dynamic: description
Dynamic: description-content-type
Dynamic: home-page
Dynamic: license
Dynamic: license-file
Dynamic: project-url
Dynamic: provides-extra
Dynamic: requires-dist
Dynamic: requires-python
Dynamic: summary
